smoothtext/__init__.py
smoothtext/backend.py
smoothtext/language.py
smoothtext/py.typed
smoothtext/readability.py
smoothtext/smoothtext.py
smoothtext/internal/__init__.py
smoothtext/internal/syllabifier.py
smoothtext/internal/tokenizer.py
smoothtext-0.4.0.dist-info/LICENSE
smoothtext-0.4.0.dist-info/METADATA
smoothtext-0.4.0.dist-info/WHEEL
smoothtext-0.4.0.dist-info/top_level.txt
smoothtext-0.4.0.dist-info/RECORD
