Metadata-Version: 2.2
Name: smoothtext
Version: 0.4.0
Summary: A Python library for readability and textual metrics analysis, supporting multiple languages.
Author-email: Tuğrul Güngör <contact@tugrulgungor.me>
License: MIT
Project-URL: Documentation, https://smoothtext.github.io
Project-URL: Homepage, https://github.com/smoothtext/smoothtext
Project-URL: Issues, https://github.com/smoothtext/smoothtext/issues
Project-URL: Source, https://github.com/smoothtext/smoothtext
Keywords: readability,text-processing,nlp,linguistics,text-analysis,syllables,english,german,russian,turkish,atesman,automated-readability-index,bezirci-yilmaz,flesch,flesch-kincaid,matskovskiy,wiener-sachtextformel
Classifier: Development Status :: 4 - Beta
Classifier: License :: OSI Approved :: MIT License
Classifier: Natural Language :: English
Classifier: Natural Language :: German
Classifier: Natural Language :: Russian
Classifier: Natural Language :: Turkish
Classifier: Operating System :: OS Independent
Classifier: Programming Language :: Python :: 3
Classifier: Programming Language :: Python :: 3.10
Classifier: Programming Language :: Python :: 3.11
Classifier: Programming Language :: Python :: 3.12
Classifier: Topic :: Text Processing
Requires-Python: <3.13,>=3.10
License-File: LICENSE
Provides-Extra: nltk
Requires-Dist: nltk>=3.9.1; extra == "nltk"
Provides-Extra: stanza
Requires-Dist: stanza>=1.10.1; extra == "stanza"
Requires-Dist: cmudict>=1.0.32; extra == "stanza"
Provides-Extra: dev
Requires-Dist: black>=23.0.0; extra == "dev"
Requires-Dist: isort>=5.12.0; extra == "dev"
Requires-Dist: mypy>=1.5.0; extra == "dev"
Requires-Dist: pip-tools>=7.3.0; extra == "dev"
Provides-Extra: test
Requires-Dist: pytest>=7.4.0; extra == "test"
Requires-Dist: pytest-cov>=4.1.0; extra == "test"
Provides-Extra: docs
Requires-Dist: sphinx>=7.0.0; extra == "docs"
Requires-Dist: sphinx-rtd-theme>=1.3.0; extra == "docs"
Provides-Extra: all
Requires-Dist: smoothtext[dev,docs,nltk,stanza,test]; extra == "all"
